pygrove/__init__.py
pygrove/pygrove.py
pygrove-1.6.0.dist-info/LICENSE
pygrove-1.6.0.dist-info/METADATA
pygrove-1.6.0.dist-info/WHEEL
pygrove-1.6.0.dist-info/top_level.txt
pygrove-1.6.0.dist-info/RECORD
