Metadata-Version: 2.1
Name: pygrove
Version: 1.6.0
Summary: Automate standard NLP impports
Home-page: https://github.com/sileod/pygrove/
Classifier: Programming Language :: Python :: 3
Classifier: License :: OSI Approved :: BSD License
Classifier: Intended Audience :: Developers
Requires-Python: >=3.6
License-File: LICENSE
Requires-Dist: pyforest
